topsis/__init__.py
topsis/topsis.py
Topsis_Vanshaj_102003346-1.0.8.dist-info/License.txt
Topsis_Vanshaj_102003346-1.0.8.dist-info/METADATA
Topsis_Vanshaj_102003346-1.0.8.dist-info/WHEEL
Topsis_Vanshaj_102003346-1.0.8.dist-info/entry_points.txt
Topsis_Vanshaj_102003346-1.0.8.dist-info/top_level.txt
Topsis_Vanshaj_102003346-1.0.8.dist-info/RECORD
